{
  "date": "2025-09-26",
  "generated_at": "2025-09-26T03:30:31.979+09:00",
  "account": "asoble_ohmeotsu",
  "source": "ig_graph_v23.0",
  "items": [
    {
      "id": "18322429600212110",
      "permalink": "https://instagram.com/stories/asoble_ohmeotsu/3729290963853097444",
      "timestamp": "2025-09-25T07:42:24+0000",
      "metrics": {}
    },
    {
      "id": "18070651189946336",
      "permalink": "https://instagram.com/stories/asoble_ohmeotsu/3729284676381651344",
      "timestamp": "2025-09-25T07:29:54+0000",
      "metrics": {}
    }
  ]
}