[
  {
    "t": "2025-09-20T09:12:34.854+09:00",
    "followers": 0
  },
  {
    "t": "2025-10-08T12:27:20.006+09:00",
    "followers": 795
  },
  {
    "t": "2025-10-08T12:37:21.770+09:00",
    "followers": 795
  },
  {
    "t": "2025-10-08T13:18:47.613+09:00",
    "followers": 795
  },
  {
    "t": "2025-10-08T14:16:03.752+09:00",
    "followers": 795
  },
  {
    "t": "2025-10-08T15:23:47.131+09:00",
    "followers": 795
  },
  {
    "t": "2025-10-08T16:15:34.736+09:00",
    "followers": 795
  },
  {
    "t": "2025-10-08T17:22:01.202+09:00",
    "followers": 795
  },
  {
    "t": "2025-10-08T18:17:38.151+09:00",
    "followers": 795
  },
  {
    "t": "2025-10-08T19:16:43.461+09:00",
    "followers": 795
  },
  {
    "t": "2025-10-08T20:13:24.165+09:00",
    "followers": 795
  },
  {
    "t": "2025-10-08T21:32:48.443+09:00",
    "followers": 795
  },
  {
    "t": "2025-10-08T22:27:03.962+09:00",
    "followers": 795
  },
  {
    "t": "2025-10-08T23:16:19.376+09:00",
    "followers": 795
  },
  {
    "t": "2025-10-09T00:17:13.900+09:00",
    "followers": 795
  },
  {
    "t": "2025-10-09T01:19:48.676+09:00",
    "followers": 795
  },
  {
    "t": "2025-10-09T02:14:21.958+09:00",
    "followers": 795
  },
  {
    "t": "2025-10-09T03:23:22.518+09:00",
    "followers": 795
  },
  {
    "t": "2025-10-09T04:12:39.833+09:00",
    "followers": 795
  },
  {
    "t": "2025-10-09T05:17:25.018+09:00",
    "followers": 795
  },
  {
    "t": "2025-10-09T06:14:32.680+09:00",
    "followers": 795
  },
  {
    "t": "2025-10-09T07:14:54.006+09:00",
    "followers": 795
  },
  {
    "t": "2025-10-09T08:14:24.482+09:00",
    "followers": 795
  },
  {
    "t": "2025-10-09T10:09:24.461+09:00",
    "followers": 795
  },
  {
    "t": "2025-10-09T11:58:05.212+09:00",
    "followers": 795
  },
  {
    "t": "2025-10-09T12:33:02.732+09:00",
    "followers": 795
  },
  {
    "t": "2025-10-09T13:18:59.949+09:00",
    "followers": 795
  },
  {
    "t": "2025-10-09T14:16:03.498+09:00",
    "followers": 795
  },
  {
    "t": "2025-10-09T15:23:57.381+09:00",
    "followers": 795
  },
  {
    "t": "2025-10-09T16:15:42.201+09:00",
    "followers": 795
  },
  {
    "t": "2025-10-09T17:21:23.120+09:00",
    "followers": 795
  },
  {
    "t": "2025-10-09T18:17:07.408+09:00",
    "followers": 795
  },
  {
    "t": "2025-10-09T19:17:24.414+09:00",
    "followers": 795
  },
  {
    "t": "2025-10-09T20:13:50.055+09:00",
    "followers": 795
  },
  {
    "t": "2025-10-09T21:32:37.136+09:00",
    "followers": 795
  },
  {
    "t": "2025-10-09T22:27:42.671+09:00",
    "followers": 795
  },
  {
    "t": "2025-10-09T23:16:09.734+09:00",
    "followers": 795
  },
  {
    "t": "2025-10-10T00:29:17.756+09:00",
    "followers": 795
  },
  {
    "t": "2025-10-10T01:40:08.515+09:00",
    "followers": 795
  },
  {
    "t": "2025-10-10T02:14:41.871+09:00",
    "followers": 795
  },
  {
    "t": "2025-10-10T03:22:34.534+09:00",
    "followers": 795
  },
  {
    "t": "2025-10-10T04:13:55.868+09:00",
    "followers": 795
  },
  {
    "t": "2025-10-10T05:18:00.360+09:00",
    "followers": 795
  },
  {
    "t": "2025-10-10T06:14:39.122+09:00",
    "followers": 795
  },
  {
    "t": "2025-10-10T07:14:12.730+09:00",
    "followers": 795
  },
  {
    "t": "2025-10-10T08:14:19.425+09:00",
    "followers": 795
  },
  {
    "t": "2025-10-10T10:09:10.471+09:00",
    "followers": 796
  },
  {
    "t": "2025-10-10T11:58:31.216+09:00",
    "followers": 796
  },
  {
    "t": "2025-10-10T12:34:15.362+09:00",
    "followers": 796
  },
  {
    "t": "2025-10-10T13:18:40.256+09:00",
    "followers": 796
  },
  {
    "t": "2025-10-10T14:15:57.001+09:00",
    "followers": 796
  },
  {
    "t": "2025-10-10T15:23:38.984+09:00",
    "followers": 796
  },
  {
    "t": "2025-10-10T16:15:23.411+09:00",
    "followers": 796
  },
  {
    "t": "2025-10-10T17:21:08.536+09:00",
    "followers": 796
  },
  {
    "t": "2025-10-10T18:17:53.234+09:00",
    "followers": 796
  },
  {
    "t": "2025-10-10T19:17:44.812+09:00",
    "followers": 796
  },
  {
    "t": "2025-10-10T20:13:56.245+09:00",
    "followers": 797
  },
  {
    "t": "2025-10-10T21:32:16.069+09:00",
    "followers": 797
  },
  {
    "t": "2025-10-10T22:25:50.672+09:00",
    "followers": 797
  },
  {
    "t": "2025-10-10T23:15:49.654+09:00",
    "followers": 797
  },
  {
    "t": "2025-10-11T00:16:13.361+09:00",
    "followers": 797
  },
  {
    "t": "2025-10-11T01:19:45.091+09:00",
    "followers": 797
  },
  {
    "t": "2025-10-11T02:14:58.803+09:00",
    "followers": 797
  },
  {
    "t": "2025-10-11T03:22:26.466+09:00",
    "followers": 797
  },
  {
    "t": "2025-10-11T04:13:07.818+09:00",
    "followers": 797
  },
  {
    "t": "2025-10-11T05:17:14.944+09:00",
    "followers": 797
  },
  {
    "t": "2025-10-11T06:13:18.940+09:00",
    "followers": 797
  },
  {
    "t": "2025-10-11T07:14:12.156+09:00",
    "followers": 797
  },
  {
    "t": "2025-10-11T08:14:01.474+09:00",
    "followers": 797
  },
  {
    "t": "2025-10-11T10:06:34.737+09:00",
    "followers": 798
  },
  {
    "t": "2025-10-11T11:51:18.428+09:00",
    "followers": 798
  },
  {
    "t": "2025-10-11T12:23:53.128+09:00",
    "followers": 798
  },
  {
    "t": "2025-10-11T13:17:52.227+09:00",
    "followers": 798
  },
  {
    "t": "2025-10-11T14:14:14.257+09:00",
    "followers": 798
  },
  {
    "t": "2025-10-11T15:20:51.064+09:00",
    "followers": 798
  },
  {
    "t": "2025-10-11T16:13:53.596+09:00",
    "followers": 798
  },
  {
    "t": "2025-10-11T17:18:31.060+09:00",
    "followers": 798
  },
  {
    "t": "2025-10-11T18:14:12.170+09:00",
    "followers": 798
  },
  {
    "t": "2025-10-11T19:14:42.515+09:00",
    "followers": 798
  },
  {
    "t": "2025-10-11T20:11:40.217+09:00",
    "followers": 798
  },
  {
    "t": "2025-10-11T21:27:41.613+09:00",
    "followers": 798
  },
  {
    "t": "2025-10-11T22:19:01.299+09:00",
    "followers": 798
  },
  {
    "t": "2025-10-11T23:12:18.468+09:00",
    "followers": 798
  },
  {
    "t": "2025-10-12T00:13:38.422+09:00",
    "followers": 798
  },
  {
    "t": "2025-10-12T01:16:48.844+09:00",
    "followers": 798
  },
  {
    "t": "2025-10-12T02:11:58.948+09:00",
    "followers": 798
  },
  {
    "t": "2025-10-12T03:19:00.596+09:00",
    "followers": 798
  },
  {
    "t": "2025-10-12T04:10:56.689+09:00",
    "followers": 798
  },
  {
    "t": "2025-10-12T05:15:20.616+09:00",
    "followers": 798
  },
  {
    "t": "2025-10-12T06:12:29.901+09:00",
    "followers": 798
  },
  {
    "t": "2025-10-12T07:13:57.951+09:00",
    "followers": 798
  },
  {
    "t": "2025-10-12T08:14:05.767+09:00",
    "followers": 798
  },
  {
    "t": "2025-10-12T10:12:26.014+09:00",
    "followers": 798
  },
  {
    "t": "2025-10-12T12:00:13.770+09:00",
    "followers": 799
  },
  {
    "t": "2025-10-12T12:36:54.659+09:00",
    "followers": 799
  },
  {
    "t": "2025-10-12T13:18:14.605+09:00",
    "followers": 799
  },
  {
    "t": "2025-10-12T14:14:37.959+09:00",
    "followers": 799
  },
  {
    "t": "2025-10-12T15:21:25.090+09:00",
    "followers": 799
  },
  {
    "t": "2025-10-12T16:14:07.965+09:00",
    "followers": 800
  },
  {
    "t": "2025-10-12T17:18:30.776+09:00",
    "followers": 799
  },
  {
    "t": "2025-10-12T18:14:13.568+09:00",
    "followers": 799
  },
  {
    "t": "2025-10-12T19:14:34.525+09:00",
    "followers": 799
  },
  {
    "t": "2025-10-12T20:11:35.933+09:00",
    "followers": 799
  },
  {
    "t": "2025-10-12T21:28:25.503+09:00",
    "followers": 799
  },
  {
    "t": "2025-10-12T22:19:28.027+09:00",
    "followers": 799
  },
  {
    "t": "2025-10-12T23:12:59.414+09:00",
    "followers": 799
  },
  {
    "t": "2025-10-13T00:13:58.829+09:00",
    "followers": 799
  },
  {
    "t": "2025-10-13T01:17:12.731+09:00",
    "followers": 799
  },
  {
    "t": "2025-10-13T02:13:02.544+09:00",
    "followers": 799
  },
  {
    "t": "2025-10-13T03:19:58.629+09:00",
    "followers": 799
  },
  {
    "t": "2025-10-13T04:11:32.118+09:00",
    "followers": 799
  },
  {
    "t": "2025-10-13T05:16:20.428+09:00",
    "followers": 799
  },
  {
    "t": "2025-10-13T06:13:13.111+09:00",
    "followers": 799
  },
  {
    "t": "2025-10-13T07:14:19.282+09:00",
    "followers": 799
  },
  {
    "t": "2025-10-13T08:13:52.350+09:00",
    "followers": 799
  },
  {
    "t": "2025-10-13T10:14:36.280+09:00",
    "followers": 799
  },
  {
    "t": "2025-10-13T12:07:22.853+09:00",
    "followers": 799
  },
  {
    "t": "2025-10-13T13:19:33.313+09:00",
    "followers": 799
  },
  {
    "t": "2025-10-13T14:16:35.163+09:00",
    "followers": 799
  },
  {
    "t": "2025-10-13T15:25:25.704+09:00",
    "followers": 799
  },
  {
    "t": "2025-10-13T16:17:05.127+09:00",
    "followers": 799
  },
  {
    "t": "2025-10-13T17:22:47.265+09:00",
    "followers": 799
  },
  {
    "t": "2025-10-13T18:19:44.428+09:00",
    "followers": 799
  },
  {
    "t": "2025-10-13T19:19:32.983+09:00",
    "followers": 799
  },
  {
    "t": "2025-10-13T20:13:57.479+09:00",
    "followers": 799
  },
  {
    "t": "2025-10-13T21:32:29.968+09:00",
    "followers": 799
  },
  {
    "t": "2025-10-13T22:27:40.493+09:00",
    "followers": 799
  },
  {
    "t": "2025-10-13T23:16:45.479+09:00",
    "followers": 799
  },
  {
    "t": "2025-10-14T00:16:45.845+09:00",
    "followers": 799
  },
  {
    "t": "2025-10-14T01:20:07.686+09:00",
    "followers": 799
  },
  {
    "t": "2025-10-14T02:14:07.313+09:00",
    "followers": 799
  },
  {
    "t": "2025-10-14T03:22:12.125+09:00",
    "followers": 799
  },
  {
    "t": "2025-10-14T04:12:59.852+09:00",
    "followers": 799
  },
  {
    "t": "2025-10-14T05:17:46.179+09:00",
    "followers": 799
  },
  {
    "t": "2025-10-14T06:14:15.614+09:00",
    "followers": 799
  },
  {
    "t": "2025-10-14T07:15:20.915+09:00",
    "followers": 799
  },
  {
    "t": "2025-10-14T08:14:12.747+09:00",
    "followers": 799
  },
  {
    "t": "2025-10-14T10:09:26.499+09:00",
    "followers": 799
  },
  {
    "t": "2025-10-14T11:58:36.699+09:00",
    "followers": 799
  },
  {
    "t": "2025-10-14T12:35:01.665+09:00",
    "followers": 799
  },
  {
    "t": "2025-10-14T13:19:18.437+09:00",
    "followers": 799
  },
  {
    "t": "2025-10-14T14:15:24.749+09:00",
    "followers": 799
  },
  {
    "t": "2025-10-14T15:24:34.449+09:00",
    "followers": 799
  },
  {
    "t": "2025-10-14T16:17:01.703+09:00",
    "followers": 799
  },
  {
    "t": "2025-10-14T17:20:47.512+09:00",
    "followers": 799
  },
  {
    "t": "2025-10-14T18:18:14.743+09:00",
    "followers": 799
  },
  {
    "t": "2025-10-14T19:17:08.604+09:00",
    "followers": 799
  },
  {
    "t": "2025-10-14T20:13:49.629+09:00",
    "followers": 799
  },
  {
    "t": "2025-10-14T21:34:03.069+09:00",
    "followers": 799
  },
  {
    "t": "2025-10-14T22:27:48.518+09:00",
    "followers": 799
  },
  {
    "t": "2025-10-14T23:16:52.472+09:00",
    "followers": 799
  },
  {
    "t": "2025-10-15T00:18:14.027+09:00",
    "followers": 799
  },
  {
    "t": "2025-10-15T01:20:11.784+09:00",
    "followers": 799
  },
  {
    "t": "2025-10-15T02:14:44.595+09:00",
    "followers": 799
  },
  {
    "t": "2025-10-15T03:23:19.041+09:00",
    "followers": 799
  },
  {
    "t": "2025-10-15T04:13:01.822+09:00",
    "followers": 799
  },
  {
    "t": "2025-10-15T05:17:37.823+09:00",
    "followers": 799
  },
  {
    "t": "2025-10-15T06:14:31.316+09:00",
    "followers": 799
  },
  {
    "t": "2025-10-15T07:15:08.983+09:00",
    "followers": 799
  },
  {
    "t": "2025-10-15T08:14:28.289+09:00",
    "followers": 799
  },
  {
    "t": "2025-10-15T10:11:18.037+09:00",
    "followers": 800
  },
  {
    "t": "2025-10-15T12:02:53.044+09:00",
    "followers": 800
  },
  {
    "t": "2025-10-15T13:19:07.269+09:00",
    "followers": 800
  },
  {
    "t": "2025-10-15T14:15:53.910+09:00",
    "followers": 800
  },
  {
    "t": "2025-10-15T15:24:31.555+09:00",
    "followers": 800
  },
  {
    "t": "2025-10-15T16:17:01.806+09:00",
    "followers": 800
  },
  {
    "t": "2025-10-15T17:22:15.333+09:00",
    "followers": 800
  },
  {
    "t": "2025-10-15T18:17:44.055+09:00",
    "followers": 800
  },
  {
    "t": "2025-10-15T19:18:10.236+09:00",
    "followers": 800
  },
  {
    "t": "2025-10-15T20:13:51.980+09:00",
    "followers": 800
  },
  {
    "t": "2025-10-15T21:34:06.577+09:00",
    "followers": 800
  },
  {
    "t": "2025-10-15T22:29:35.951+09:00",
    "followers": 800
  },
  {
    "t": "2025-10-15T23:22:09.670+09:00",
    "followers": 800
  },
  {
    "t": "2025-10-16T00:16:56.704+09:00",
    "followers": 800
  },
  {
    "t": "2025-10-16T01:17:17.920+09:00",
    "followers": 800
  },
  {
    "t": "2025-10-16T02:14:38.750+09:00",
    "followers": 800
  },
  {
    "t": "2025-10-16T03:23:10.376+09:00",
    "followers": 800
  },
  {
    "t": "2025-10-16T04:13:22.144+09:00",
    "followers": 800
  },
  {
    "t": "2025-10-16T05:18:37.579+09:00",
    "followers": 800
  },
  {
    "t": "2025-10-16T06:14:18.992+09:00",
    "followers": 800
  },
  {
    "t": "2025-10-16T07:13:52.789+09:00",
    "followers": 800
  },
  {
    "t": "2025-10-16T08:14:11.822+09:00",
    "followers": 800
  },
  {
    "t": "2025-10-16T10:10:49.609+09:00",
    "followers": 801
  },
  {
    "t": "2025-10-16T12:00:59.115+09:00",
    "followers": 801
  },
  {
    "t": "2025-10-16T12:40:19.012+09:00",
    "followers": 800
  },
  {
    "t": "2025-10-16T13:18:47.164+09:00",
    "followers": 800
  },
  {
    "t": "2025-10-16T14:15:53.105+09:00",
    "followers": 800
  },
  {
    "t": "2025-10-16T15:23:46.730+09:00",
    "followers": 800
  },
  {
    "t": "2025-10-16T16:16:01.310+09:00",
    "followers": 800
  },
  {
    "t": "2025-10-16T17:22:19.950+09:00",
    "followers": 800
  },
  {
    "t": "2025-10-16T18:18:00.832+09:00",
    "followers": 800
  },
  {
    "t": "2025-10-16T19:18:22.204+09:00",
    "followers": 800
  },
  {
    "t": "2025-10-16T20:14:15.855+09:00",
    "followers": 800
  },
  {
    "t": "2025-10-16T21:34:16.820+09:00",
    "followers": 800
  },
  {
    "t": "2025-10-16T22:28:38.282+09:00",
    "followers": 800
  },
  {
    "t": "2025-10-16T23:16:52.947+09:00",
    "followers": 800
  },
  {
    "t": "2025-10-17T00:17:54.797+09:00",
    "followers": 800
  },
  {
    "t": "2025-10-17T01:20:51.482+09:00",
    "followers": 800
  },
  {
    "t": "2025-10-17T02:14:36.631+09:00",
    "followers": 800
  },
  {
    "t": "2025-10-17T03:22:58.547+09:00",
    "followers": 800
  },
  {
    "t": "2025-10-17T04:12:13.030+09:00",
    "followers": 800
  },
  {
    "t": "2025-10-17T05:17:52.070+09:00",
    "followers": 800
  },
  {
    "t": "2025-10-17T06:14:16.047+09:00",
    "followers": 800
  },
  {
    "t": "2025-10-17T07:12:32.536+09:00",
    "followers": 800
  },
  {
    "t": "2025-10-17T08:14:27.353+09:00",
    "followers": 800
  },
  {
    "t": "2025-10-17T10:10:48.465+09:00",
    "followers": 800
  },
  {
    "t": "2025-10-17T11:59:31.804+09:00",
    "followers": 800
  },
  {
    "t": "2025-10-17T12:36:47.047+09:00",
    "followers": 800
  },
  {
    "t": "2025-10-17T13:19:13.607+09:00",
    "followers": 800
  },
  {
    "t": "2025-10-17T14:15:26.174+09:00",
    "followers": 800
  },
  {
    "t": "2025-10-17T15:23:24.512+09:00",
    "followers": 800
  },
  {
    "t": "2025-10-17T16:15:55.643+09:00",
    "followers": 800
  },
  {
    "t": "2025-10-17T17:22:12.134+09:00",
    "followers": 800
  },
  {
    "t": "2025-10-17T18:17:54.660+09:00",
    "followers": 800
  },
  {
    "t": "2025-10-17T19:17:47.297+09:00",
    "followers": 800
  },
  {
    "t": "2025-10-17T20:13:28.087+09:00",
    "followers": 800
  },
  {
    "t": "2025-10-17T21:32:38.821+09:00",
    "followers": 800
  },
  {
    "t": "2025-10-17T22:25:53.869+09:00",
    "followers": 800
  },
  {
    "t": "2025-10-17T23:16:10.599+09:00",
    "followers": 800
  },
  {
    "t": "2025-10-18T00:16:32.144+09:00",
    "followers": 800
  },
  {
    "t": "2025-10-18T01:20:00.484+09:00",
    "followers": 800
  },
  {
    "t": "2025-10-18T02:14:17.873+09:00",
    "followers": 800
  },
  {
    "t": "2025-10-18T03:20:39.638+09:00",
    "followers": 800
  },
  {
    "t": "2025-10-18T04:13:20.717+09:00",
    "followers": 800
  },
  {
    "t": "2025-10-18T05:18:31.364+09:00",
    "followers": 800
  },
  {
    "t": "2025-10-18T06:14:36.591+09:00",
    "followers": 800
  },
  {
    "t": "2025-10-18T07:14:44.487+09:00",
    "followers": 800
  },
  {
    "t": "2025-10-18T08:14:17.024+09:00",
    "followers": 800
  },
  {
    "t": "2025-10-18T10:07:15.116+09:00",
    "followers": 800
  },
  {
    "t": "2025-10-18T11:54:16.793+09:00",
    "followers": 800
  },
  {
    "t": "2025-10-18T12:26:05.382+09:00",
    "followers": 800
  },
  {
    "t": "2025-10-18T13:18:28.682+09:00",
    "followers": 800
  },
  {
    "t": "2025-10-18T14:14:56.091+09:00",
    "followers": 800
  },
  {
    "t": "2025-10-18T15:21:39.044+09:00",
    "followers": 800
  },
  {
    "t": "2025-10-18T16:14:27.693+09:00",
    "followers": 800
  },
  {
    "t": "2025-10-18T17:19:48.396+09:00",
    "followers": 800
  },
  {
    "t": "2025-10-18T18:15:15.840+09:00",
    "followers": 800
  },
  {
    "t": "2025-10-18T19:15:10.866+09:00",
    "followers": 800
  },
  {
    "t": "2025-10-18T20:12:31.256+09:00",
    "followers": 800
  },
  {
    "t": "2025-10-18T21:29:10.470+09:00",
    "followers": 800
  },
  {
    "t": "2025-10-18T22:20:44.958+09:00",
    "followers": 800
  },
  {
    "t": "2025-10-18T23:13:24.235+09:00",
    "followers": 800
  },
  {
    "t": "2025-10-19T00:14:27.838+09:00",
    "followers": 800
  },
  {
    "t": "2025-10-19T01:17:54.859+09:00",
    "followers": 800
  },
  {
    "t": "2025-10-19T02:12:44.467+09:00",
    "followers": 800
  },
  {
    "t": "2025-10-19T03:20:28.467+09:00",
    "followers": 800
  },
  {
    "t": "2025-10-19T04:11:57.117+09:00",
    "followers": 800
  },
  {
    "t": "2025-10-19T05:16:17.259+09:00",
    "followers": 800
  },
  {
    "t": "2025-10-19T06:13:23.910+09:00",
    "followers": 800
  },
  {
    "t": "2025-10-19T07:14:24.694+09:00",
    "followers": 800
  },
  {
    "t": "2025-10-19T08:14:18.540+09:00",
    "followers": 800
  },
  {
    "t": "2025-10-19T10:19:16.260+09:00",
    "followers": 800
  },
  {
    "t": "2025-10-19T12:13:41.831+09:00",
    "followers": 800
  },
  {
    "t": "2025-10-19T13:19:56.900+09:00",
    "followers": 800
  },
  {
    "t": "2025-10-19T14:15:37.839+09:00",
    "followers": 800
  },
  {
    "t": "2025-10-19T15:22:55.737+09:00",
    "followers": 800
  },
  {
    "t": "2025-10-19T16:14:12.710+09:00",
    "followers": 800
  },
  {
    "t": "2025-10-19T17:18:58.551+09:00",
    "followers": 800
  },
  {
    "t": "2025-10-19T18:14:56.366+09:00",
    "followers": 800
  },
  {
    "t": "2025-10-19T19:15:21.650+09:00",
    "followers": 800
  },
  {
    "t": "2025-10-19T20:12:04.536+09:00",
    "followers": 799
  },
  {
    "t": "2025-10-19T21:28:58.923+09:00",
    "followers": 799
  },
  {
    "t": "2025-10-19T22:21:06.000+09:00",
    "followers": 799
  },
  {
    "t": "2025-10-19T23:13:43.795+09:00",
    "followers": 799
  },
  {
    "t": "2025-10-20T00:14:31.187+09:00",
    "followers": 799
  },
  {
    "t": "2025-10-20T01:17:25.823+09:00",
    "followers": 799
  },
  {
    "t": "2025-10-20T02:13:38.391+09:00",
    "followers": 799
  },
  {
    "t": "2025-10-20T03:20:39.404+09:00",
    "followers": 799
  },
  {
    "t": "2025-10-20T04:12:10.212+09:00",
    "followers": 799
  },
  {
    "t": "2025-10-20T05:17:03.659+09:00",
    "followers": 799
  },
  {
    "t": "2025-10-20T06:13:36.999+09:00",
    "followers": 799
  },
  {
    "t": "2025-10-20T07:14:57.900+09:00",
    "followers": 799
  },
  {
    "t": "2025-10-20T08:14:30.727+09:00",
    "followers": 799
  },
  {
    "t": "2025-10-20T10:16:30.174+09:00",
    "followers": 799
  },
  {
    "t": "2025-10-20T12:13:23.222+09:00",
    "followers": 799
  },
  {
    "t": "2025-10-20T13:22:51.010+09:00",
    "followers": 799
  },
  {
    "t": "2025-10-20T14:17:21.782+09:00",
    "followers": 799
  },
  {
    "t": "2025-10-20T15:25:29.025+09:00",
    "followers": 799
  },
  {
    "t": "2025-10-20T16:17:24.694+09:00",
    "followers": 799
  },
  {
    "t": "2025-10-20T17:22:38.506+09:00",
    "followers": 799
  },
  {
    "t": "2025-10-20T18:19:38.818+09:00",
    "followers": 799
  },
  {
    "t": "2025-10-20T19:18:35.453+09:00",
    "followers": 799
  },
  {
    "t": "2025-10-20T20:15:20.262+09:00",
    "followers": 799
  },
  {
    "t": "2025-10-20T21:33:57.730+09:00",
    "followers": 799
  },
  {
    "t": "2025-10-20T22:27:35.836+09:00",
    "followers": 799
  },
  {
    "t": "2025-10-20T23:16:21.998+09:00",
    "followers": 799
  },
  {
    "t": "2025-10-21T00:16:36.366+09:00",
    "followers": 799
  },
  {
    "t": "2025-10-21T01:20:10.158+09:00",
    "followers": 799
  },
  {
    "t": "2025-10-21T02:14:22.939+09:00",
    "followers": 799
  },
  {
    "t": "2025-10-21T03:24:02.882+09:00",
    "followers": 799
  },
  {
    "t": "2025-10-21T04:14:25.992+09:00",
    "followers": 799
  },
  {
    "t": "2025-10-21T05:19:03.713+09:00",
    "followers": 799
  },
  {
    "t": "2025-10-21T06:15:43.402+09:00",
    "followers": 799
  },
  {
    "t": "2025-10-21T07:14:59.441+09:00",
    "followers": 799
  },
  {
    "t": "2025-10-21T08:14:50.925+09:00",
    "followers": 799
  },
  {
    "t": "2025-10-21T10:13:06.518+09:00",
    "followers": 799
  },
  {
    "t": "2025-10-21T12:03:44.832+09:00",
    "followers": 799
  },
  {
    "t": "2025-10-21T13:19:22.272+09:00",
    "followers": 799
  },
  {
    "t": "2025-10-21T14:16:27.439+09:00",
    "followers": 799
  },
  {
    "t": "2025-10-21T15:24:12.118+09:00",
    "followers": 799
  },
  {
    "t": "2025-10-21T16:17:24.248+09:00",
    "followers": 799
  },
  {
    "t": "2025-10-21T17:23:00.239+09:00",
    "followers": 799
  },
  {
    "t": "2025-10-21T18:18:05.464+09:00",
    "followers": 799
  },
  {
    "t": "2025-10-21T19:18:12.443+09:00",
    "followers": 799
  },
  {
    "t": "2025-10-21T20:14:11.077+09:00",
    "followers": 799
  },
  {
    "t": "2025-10-21T21:33:55.644+09:00",
    "followers": 799
  },
  {
    "t": "2025-10-21T22:31:27.185+09:00",
    "followers": 799
  },
  {
    "t": "2025-10-21T23:16:12.661+09:00",
    "followers": 799
  },
  {
    "t": "2025-10-22T00:17:24.757+09:00",
    "followers": 799
  },
  {
    "t": "2025-10-22T01:21:35.011+09:00",
    "followers": 799
  },
  {
    "t": "2025-10-22T02:16:02.861+09:00",
    "followers": 799
  },
  {
    "t": "2025-10-22T03:22:42.322+09:00",
    "followers": 799
  },
  {
    "t": "2025-10-22T04:14:03.500+09:00",
    "followers": 799
  },
  {
    "t": "2025-10-22T05:18:40.057+09:00",
    "followers": 799
  },
  {
    "t": "2025-10-22T06:15:11.391+09:00",
    "followers": 799
  },
  {
    "t": "2025-10-22T07:15:06.380+09:00",
    "followers": 799
  },
  {
    "t": "2025-10-22T08:15:54.140+09:00",
    "followers": 799
  },
  {
    "t": "2025-10-22T10:14:41.652+09:00",
    "followers": 799
  },
  {
    "t": "2025-10-22T12:08:47.928+09:00",
    "followers": 799
  },
  {
    "t": "2025-10-22T13:19:56.319+09:00",
    "followers": 799
  },
  {
    "t": "2025-10-22T14:16:49.769+09:00",
    "followers": 799
  },
  {
    "t": "2025-10-22T15:25:00.783+09:00",
    "followers": 799
  },
  {
    "t": "2025-10-22T16:16:28.689+09:00",
    "followers": 799
  },
  {
    "t": "2025-10-22T17:24:16.942+09:00",
    "followers": 799
  },
  {
    "t": "2025-10-22T18:19:15.028+09:00",
    "followers": 799
  },
  {
    "t": "2025-10-22T19:18:55.608+09:00",
    "followers": 800
  },
  {
    "t": "2025-10-22T20:14:59.870+09:00",
    "followers": 800
  },
  {
    "t": "2025-10-22T21:34:23.980+09:00",
    "followers": 800
  },
  {
    "t": "2025-10-22T22:31:29.104+09:00",
    "followers": 800
  },
  {
    "t": "2025-10-22T23:18:06.981+09:00",
    "followers": 800
  },
  {
    "t": "2025-10-23T00:16:48.501+09:00",
    "followers": 800
  },
  {
    "t": "2025-10-23T01:21:46.698+09:00",
    "followers": 800
  },
  {
    "t": "2025-10-23T02:15:40.330+09:00",
    "followers": 800
  },
  {
    "t": "2025-10-23T03:24:47.581+09:00",
    "followers": 800
  },
  {
    "t": "2025-10-23T04:13:35.113+09:00",
    "followers": 800
  },
  {
    "t": "2025-10-23T05:20:18.389+09:00",
    "followers": 800
  },
  {
    "t": "2025-10-23T06:13:23.260+09:00",
    "followers": 800
  },
  {
    "t": "2025-10-23T07:13:21.857+09:00",
    "followers": 800
  },
  {
    "t": "2025-10-23T08:14:06.992+09:00",
    "followers": 800
  },
  {
    "t": "2025-10-23T10:12:39.457+09:00",
    "followers": 800
  },
  {
    "t": "2025-10-23T12:01:41.312+09:00",
    "followers": 800
  },
  {
    "t": "2025-10-23T13:19:32.928+09:00",
    "followers": 800
  },
  {
    "t": "2025-10-23T14:16:29.412+09:00",
    "followers": 800
  },
  {
    "t": "2025-10-23T15:24:27.029+09:00",
    "followers": 801
  },
  {
    "t": "2025-10-23T16:17:10.884+09:00",
    "followers": 801
  },
  {
    "t": "2025-10-23T17:22:31.343+09:00",
    "followers": 801
  },
  {
    "t": "2025-10-23T18:18:17.615+09:00",
    "followers": 801
  },
  {
    "t": "2025-10-23T19:18:02.632+09:00",
    "followers": 801
  },
  {
    "t": "2025-10-23T20:14:43.392+09:00",
    "followers": 801
  },
  {
    "t": "2025-10-23T21:34:24.741+09:00",
    "followers": 801
  },
  {
    "t": "2025-10-23T22:29:49.891+09:00",
    "followers": 801
  },
  {
    "t": "2025-10-23T23:17:25.287+09:00",
    "followers": 801
  },
  {
    "t": "2025-10-24T00:17:56.673+09:00",
    "followers": 801
  },
  {
    "t": "2025-10-24T01:20:49.248+09:00",
    "followers": 801
  },
  {
    "t": "2025-10-24T02:14:35.823+09:00",
    "followers": 801
  },
  {
    "t": "2025-10-24T03:23:24.132+09:00",
    "followers": 801
  },
  {
    "t": "2025-10-24T04:13:32.820+09:00",
    "followers": 801
  },
  {
    "t": "2025-10-24T05:17:39.611+09:00",
    "followers": 801
  },
  {
    "t": "2025-10-24T06:14:46.997+09:00",
    "followers": 801
  },
  {
    "t": "2025-10-24T07:14:45.525+09:00",
    "followers": 801
  },
  {
    "t": "2025-10-24T08:14:46.956+09:00",
    "followers": 801
  },
  {
    "t": "2025-10-24T10:08:37.381+09:00",
    "followers": 801
  },
  {
    "t": "2025-10-24T11:58:28.156+09:00",
    "followers": 801
  },
  {
    "t": "2025-10-24T12:34:37.359+09:00",
    "followers": 801
  },
  {
    "t": "2025-10-24T13:19:31.704+09:00",
    "followers": 801
  },
  {
    "t": "2025-10-24T14:16:01.580+09:00",
    "followers": 801
  },
  {
    "t": "2025-10-24T15:23:23.990+09:00",
    "followers": 801
  },
  {
    "t": "2025-10-24T16:16:30.293+09:00",
    "followers": 801
  },
  {
    "t": "2025-10-24T17:21:51.000+09:00",
    "followers": 801
  },
  {
    "t": "2025-10-24T18:18:19.464+09:00",
    "followers": 801
  },
  {
    "t": "2025-10-24T19:18:38.464+09:00",
    "followers": 801
  },
  {
    "t": "2025-10-24T20:14:45.002+09:00",
    "followers": 801
  },
  {
    "t": "2025-10-24T21:34:21.896+09:00",
    "followers": 801
  },
  {
    "t": "2025-10-24T22:28:49.104+09:00",
    "followers": 801
  },
  {
    "t": "2025-10-24T23:17:04.184+09:00",
    "followers": 801
  },
  {
    "t": "2025-10-25T00:17:36.500+09:00",
    "followers": 801
  },
  {
    "t": "2025-10-25T01:20:42.308+09:00",
    "followers": 801
  },
  {
    "t": "2025-10-25T02:14:54.252+09:00",
    "followers": 800
  },
  {
    "t": "2025-10-25T03:23:01.015+09:00",
    "followers": 800
  },
  {
    "t": "2025-10-25T04:14:03.762+09:00",
    "followers": 800
  },
  {
    "t": "2025-10-25T05:18:04.467+09:00",
    "followers": 800
  },
  {
    "t": "2025-10-25T06:14:44.794+09:00",
    "followers": 800
  },
  {
    "t": "2025-10-25T07:15:10.223+09:00",
    "followers": 800
  },
  {
    "t": "2025-10-25T08:14:40.868+09:00",
    "followers": 800
  },
  {
    "t": "2025-10-25T10:09:37.315+09:00",
    "followers": 800
  },
  {
    "t": "2025-10-25T11:59:55.613+09:00",
    "followers": 800
  },
  {
    "t": "2025-10-25T12:37:29.366+09:00",
    "followers": 800
  },
  {
    "t": "2025-10-25T13:18:37.843+09:00",
    "followers": 800
  },
  {
    "t": "2025-10-25T14:15:04.153+09:00",
    "followers": 801
  },
  {
    "t": "2025-10-25T15:21:31.643+09:00",
    "followers": 801
  },
  {
    "t": "2025-10-25T16:15:26.770+09:00",
    "followers": 801
  },
  {
    "t": "2025-10-25T17:19:05.223+09:00",
    "followers": 801
  },
  {
    "t": "2025-10-25T18:15:03.519+09:00",
    "followers": 801
  },
  {
    "t": "2025-10-25T19:15:12.799+09:00",
    "followers": 800
  },
  {
    "t": "2025-10-25T20:12:35.919+09:00",
    "followers": 800
  },
  {
    "t": "2025-10-25T21:29:07.708+09:00",
    "followers": 800
  },
  {
    "t": "2025-10-25T22:20:53.766+09:00",
    "followers": 800
  },
  {
    "t": "2025-10-25T23:13:50.652+09:00",
    "followers": 800
  },
  {
    "t": "2025-10-26T00:14:38.433+09:00",
    "followers": 800
  },
  {
    "t": "2025-10-26T01:18:10.260+09:00",
    "followers": 800
  },
  {
    "t": "2025-10-26T02:13:42.415+09:00",
    "followers": 800
  },
  {
    "t": "2025-10-26T03:20:51.685+09:00",
    "followers": 800
  },
  {
    "t": "2025-10-26T04:12:09.783+09:00",
    "followers": 800
  },
  {
    "t": "2025-10-26T05:16:45.370+09:00",
    "followers": 800
  },
  {
    "t": "2025-10-26T06:13:47.907+09:00",
    "followers": 800
  },
  {
    "t": "2025-10-26T07:14:18.502+09:00",
    "followers": 800
  },
  {
    "t": "2025-10-26T08:14:28.687+09:00",
    "followers": 800
  },
  {
    "t": "2025-10-26T10:16:48.169+09:00",
    "followers": 800
  },
  {
    "t": "2025-10-26T12:08:55.051+09:00",
    "followers": 800
  },
  {
    "t": "2025-10-26T13:18:36.002+09:00",
    "followers": 800
  },
  {
    "t": "2025-10-26T14:16:00.430+09:00",
    "followers": 800
  },
  {
    "t": "2025-10-26T15:22:20.072+09:00",
    "followers": 800
  },
  {
    "t": "2025-10-26T16:14:38.956+09:00",
    "followers": 801
  },
  {
    "t": "2025-10-26T17:19:48.181+09:00",
    "followers": 801
  },
  {
    "t": "2025-10-26T18:14:54.621+09:00",
    "followers": 801
  },
  {
    "t": "2025-10-26T19:15:39.936+09:00",
    "followers": 803
  },
  {
    "t": "2025-10-26T20:13:13.513+09:00",
    "followers": 803
  },
  {
    "t": "2025-10-26T21:29:10.663+09:00",
    "followers": 803
  },
  {
    "t": "2025-10-26T22:21:51.010+09:00",
    "followers": 803
  },
  {
    "t": "2025-10-26T23:14:11.096+09:00",
    "followers": 803
  },
  {
    "t": "2025-10-27T00:14:48.193+09:00",
    "followers": 803
  },
  {
    "t": "2025-10-27T01:18:21.559+09:00",
    "followers": 803
  },
  {
    "t": "2025-10-27T02:13:39.460+09:00",
    "followers": 803
  },
  {
    "t": "2025-10-27T03:21:06.037+09:00",
    "followers": 803
  },
  {
    "t": "2025-10-27T04:12:48.802+09:00",
    "followers": 803
  },
  {
    "t": "2025-10-27T05:17:16.903+09:00",
    "followers": 803
  },
  {
    "t": "2025-10-27T06:14:03.082+09:00",
    "followers": 803
  },
  {
    "t": "2025-10-27T07:15:15.488+09:00",
    "followers": 803
  },
  {
    "t": "2025-10-27T08:15:01.331+09:00",
    "followers": 803
  },
  {
    "t": "2025-10-27T10:18:21.506+09:00",
    "followers": 803
  },
  {
    "t": "2025-10-27T12:17:14.659+09:00",
    "followers": 803
  },
  {
    "t": "2025-10-27T13:26:54.167+09:00",
    "followers": 803
  },
  {
    "t": "2025-10-27T14:18:01.561+09:00",
    "followers": 803
  },
  {
    "t": "2025-10-27T15:27:16.652+09:00",
    "followers": 803
  },
  {
    "t": "2025-10-27T16:17:35.664+09:00",
    "followers": 803
  },
  {
    "t": "2025-10-27T17:23:29.494+09:00",
    "followers": 803
  },
  {
    "t": "2025-10-27T18:20:38.624+09:00",
    "followers": 803
  },
  {
    "t": "2025-10-27T19:19:47.770+09:00",
    "followers": 803
  },
  {
    "t": "2025-10-27T20:15:06.136+09:00",
    "followers": 803
  },
  {
    "t": "2025-10-27T21:34:32.601+09:00",
    "followers": 803
  },
  {
    "t": "2025-10-27T22:29:55.951+09:00",
    "followers": 803
  },
  {
    "t": "2025-10-27T23:17:28.402+09:00",
    "followers": 804
  },
  {
    "t": "2025-10-28T00:18:07.250+09:00",
    "followers": 804
  },
  {
    "t": "2025-10-28T01:21:09.229+09:00",
    "followers": 804
  },
  {
    "t": "2025-10-28T02:14:35.926+09:00",
    "followers": 804
  },
  {
    "t": "2025-10-28T03:23:46.896+09:00",
    "followers": 804
  },
  {
    "t": "2025-10-28T04:13:23.246+09:00",
    "followers": 804
  },
  {
    "t": "2025-10-28T05:15:57.057+09:00",
    "followers": 804
  },
  {
    "t": "2025-10-28T06:14:34.922+09:00",
    "followers": 804
  },
  {
    "t": "2025-10-28T07:14:45.559+09:00",
    "followers": 805
  },
  {
    "t": "2025-10-28T08:14:37.940+09:00",
    "followers": 805
  },
  {
    "t": "2025-10-28T10:10:44.405+09:00",
    "followers": 805
  },
  {
    "t": "2025-10-28T12:05:14.542+09:00",
    "followers": 805
  },
  {
    "t": "2025-10-28T13:19:05.848+09:00",
    "followers": 805
  },
  {
    "t": "2025-10-28T14:16:58.854+09:00",
    "followers": 805
  },
  {
    "t": "2025-10-28T15:25:18.401+09:00",
    "followers": 805
  },
  {
    "t": "2025-10-28T16:16:34.583+09:00",
    "followers": 805
  },
  {
    "t": "2025-10-28T17:22:01.130+09:00",
    "followers": 805
  },
  {
    "t": "2025-10-28T18:17:42.962+09:00",
    "followers": 805
  },
  {
    "t": "2025-10-28T19:18:28.795+09:00",
    "followers": 805
  },
  {
    "t": "2025-10-28T20:13:50.218+09:00",
    "followers": 805
  },
  {
    "t": "2025-10-28T21:32:57.079+09:00",
    "followers": 805
  },
  {
    "t": "2025-10-28T22:28:00.467+09:00",
    "followers": 805
  },
  {
    "t": "2025-10-28T23:16:56.846+09:00",
    "followers": 805
  },
  {
    "t": "2025-10-29T00:18:10.148+09:00",
    "followers": 805
  },
  {
    "t": "2025-10-29T01:21:45.958+09:00",
    "followers": 805
  },
  {
    "t": "2025-10-29T02:16:11.988+09:00",
    "followers": 805
  },
  {
    "t": "2025-10-29T03:24:35.659+09:00",
    "followers": 805
  },
  {
    "t": "2025-10-29T04:13:23.803+09:00",
    "followers": 805
  },
  {
    "t": "2025-10-29T05:19:00.232+09:00",
    "followers": 805
  },
  {
    "t": "2025-10-29T06:15:04.814+09:00",
    "followers": 805
  },
  {
    "t": "2025-10-29T07:15:31.457+09:00",
    "followers": 805
  },
  {
    "t": "2025-10-29T08:15:17.098+09:00",
    "followers": 805
  }
]